shapezero/__init__.py
shapezero/py.typed
shapezero-0.1.0.dist-info/METADATA
shapezero-0.1.0.dist-info/WHEEL
shapezero-0.1.0.dist-info/licenses/LICENSE
shapezero-0.1.0.dist-info/RECORD
