Metadata-Version: 2.4
Name: shapezero
Version: 0.1.0
Summary: Swiss army knife for AI developers
Project-URL: Homepage, https://shapezeroai.com
Project-URL: Documentation, https://github.com/shapezero/shapezero
Project-URL: Repository, https://github.com/shapezero/shapezero
Project-URL: Issues, https://github.com/shapezero/shapezero/issues
Author-email: Lucas Shouse <lucas@shapezeroai.com>
License-Expression: MIT
License-File: LICENSE
Keywords: ai,anthropic,cache,claude,gpt,llm,openai,parsing,tokens,toolkit
Classifier: Development Status :: 4 - Beta
Classifier: Intended Audience :: Developers
Classifier: License :: OSI Approved :: MIT License
Classifier: Programming Language :: Python :: 3
Classifier: Programming Language :: Python :: 3.8
Classifier: Programming Language :: Python :: 3.9
Classifier: Programming Language :: Python :: 3.10
Classifier: Programming Language :: Python :: 3.11
Classifier: Programming Language :: Python :: 3.12
Classifier: Topic :: Scientific/Engineering :: Artificial Intelligence
Classifier: Topic :: Software Development :: Libraries :: Python Modules
Requires-Python: >=3.8
Provides-Extra: all
Requires-Dist: tiktoken>=0.5.0; extra == 'all'
Provides-Extra: tiktoken
Requires-Dist: tiktoken>=0.5.0; extra == 'tiktoken'
